exchangerepo/__init__.py
exchangerepo/repository/ExchangeRateRepository.py
exchangerepo/repository/InstrumentExchangeRepository.py
exchangerepo/repository/__init__.py
persuader_technology_automata_exchange_repository-0.3.1.dist-info/LICENSE
persuader_technology_automata_exchange_repository-0.3.1.dist-info/METADATA
persuader_technology_automata_exchange_repository-0.3.1.dist-info/WHEEL
persuader_technology_automata_exchange_repository-0.3.1.dist-info/top_level.txt
persuader_technology_automata_exchange_repository-0.3.1.dist-info/RECORD
