Metadata-Version: 2.1
Name: persuader-technology-automata-exchange-repository
Version: 0.3.1
Summary: Automata Exchange Repository
Author: Persuader Technology
Author-email: software@persuader.technology
License: UNLICENSE
Classifier: Programming Language :: Python :: 3
License-File: LICENSE
Requires-Dist: persuader-technology-automata-core (>=0.6.0)
Requires-Dist: persuader-technology-automata-utilities (>=0.2.3)
Requires-Dist: persuader-technology-automata-logger (>=0.0.5)
Requires-Dist: persuader-technology-automata-exchange (>=0.1.8)
Requires-Dist: persuader-technology-automata-redis (>=0.3.8)
Requires-Dist: persuader-technology-automata-timeseries (>=0.0.6)
